lstchain/__init__.py
lstchain/_version.py
lstchain/conftest.py
lstchain/ctapipe_compat.py
lstchain/onsite.py
lstchain/paths.py
lstchain/statistics.py
lstchain/version.py
lstchain/calib/__init__.py
lstchain/calib/camera/__init__.py
lstchain/calib/camera/calib.py
lstchain/calib/camera/calibration_calculator.py
lstchain/calib/camera/flatfield.py
lstchain/calib/camera/pedestals.py
lstchain/calib/camera/pixel_threshold_estimation.py
lstchain/calib/camera/pulse_time_correction.py
lstchain/calib/camera/time_correction_calculate.py
lstchain/calib/camera/time_sampling_correction.py
lstchain/calib/camera/utils.py
lstchain/calib/camera/tests/__init__.py
lstchain/calib/camera/tests/test_calculator.py
lstchain/calib/camera/tests/test_calib.py
lstchain/calib/camera/tests/test_flatfield.py
lstchain/calib/camera/tests/test_pedestals.py
lstchain/data/LST1_backg_irf_gheffi_0.40_theffi_0.40.csv
lstchain/data/LST1_backg_irf_gheffi_0.70_theffi_0.70.csv
lstchain/data/LST1_backg_irf_gheffi_0.90_theffi_0.90.csv
lstchain/data/LST1_gamma_irf_gheffi_0.40_theffi_0.40.csv
lstchain/data/LST1_gamma_irf_gheffi_0.70_theffi_0.70.csv
lstchain/data/LST1_gamma_irf_gheffi_0.90_theffi_0.90.csv
lstchain/data/SinglePhE_ResponseInPhE_expo2Gaus.dat
lstchain/data/__init__.py
lstchain/data/catB_camera_calibration_param.json
lstchain/data/ebl_dominguez11.fits.gz
lstchain/data/filters_transmission.dat
lstchain/data/lstchain_dl1ab_tune_MC_to_Crab_config.json
lstchain/data/lstchain_fit_intensity_scan_config_example.json
lstchain/data/lstchain_lhfit_config.json
lstchain/data/lstchain_mc_config.json
lstchain/data/lstchain_src_dep_config.json
lstchain/data/lstchain_standard_config.json
lstchain/data/normalised_pulse_template.py
lstchain/data/onsite_camera_calibration_param.json
lstchain/data/oversampled_pulse_LST_8dynode_pix6_20200204.dat
lstchain/datachecks/__init__.py
lstchain/datachecks/containers.py
lstchain/datachecks/dl1_checker.py
lstchain/high_level/__init__.py
lstchain/high_level/hdu_table.py
lstchain-0.11.4.dist-info/licenses/LICENSE.md
lstchain-0.11.4.dist-info/METADATA
lstchain-0.11.4.dist-info/WHEEL
lstchain-0.11.4.dist-info/entry_points.txt
lstchain-0.11.4.dist-info/top_level.txt
lstchain-0.11.4.dist-info/RECORD
