Metadata-Version: 2.4
Name: lstchain
Version: 0.11.4
Summary: Analysis chain for the CTA-LST prototype
Home-page: https://github.com/cta-observatory/cta-lstchain
Author: LST collaboration
Author-email: rlopezcoto@gmail.com
License: MIT
Requires-Python: >=3.10
License-File: LICENSE.md
Requires-Dist: astropy<8,>=6.1
Requires-Dist: bokeh~=3.0
Requires-Dist: ctapipe~=0.25.1
Requires-Dist: ctapipe_io_lst~=0.27.2
Requires-Dist: ctaplot~=0.6.4
Requires-Dist: eventio<2.0.0a0,>=1.9.1
Requires-Dist: gammapy~=1.3.0
Requires-Dist: h5py
Requires-Dist: iminuit>=2
Requires-Dist: joblib~=1.4.0
Requires-Dist: matplotlib~=3.10.0
Requires-Dist: numba
Requires-Dist: numpy
Requires-Dist: pandas
Requires-Dist: pyirf~=0.12.0
Requires-Dist: scipy>=1.8
Requires-Dist: seaborn
Requires-Dist: scikit-learn>=1.2
Requires-Dist: tables
Requires-Dist: toml
Requires-Dist: protozfits<3,>=2.7.3
Requires-Dist: pymongo
Requires-Dist: pyparsing
Provides-Extra: dev
Requires-Dist: setuptools_scm; extra == "dev"
Provides-Extra: all
Requires-Dist: pytest; extra == "all"
Requires-Dist: sphinx; extra == "all"
Requires-Dist: sphinx-automodapi; extra == "all"
Requires-Dist: sphinx_argparse; extra == "all"
Requires-Dist: sphinx_rtd_theme; extra == "all"
Requires-Dist: numpydoc; extra == "all"
Requires-Dist: nbsphinx; extra == "all"
Requires-Dist: sphinxcontrib-mermaid; extra == "all"
Requires-Dist: sphinx-togglebutton; extra == "all"
Provides-Extra: tests
Requires-Dist: pytest; extra == "tests"
Provides-Extra: docs
Requires-Dist: sphinx; extra == "docs"
Requires-Dist: sphinx-automodapi; extra == "docs"
Requires-Dist: sphinx_argparse; extra == "docs"
Requires-Dist: sphinx_rtd_theme; extra == "docs"
Requires-Dist: numpydoc; extra == "docs"
Requires-Dist: nbsphinx; extra == "docs"
Requires-Dist: sphinxcontrib-mermaid; extra == "docs"
Requires-Dist: sphinx-togglebutton; extra == "docs"
Dynamic: license-file
Dynamic: provides-extra
Dynamic: requires-dist
